AUTHOR.txt
README.txt
setup.py
collective/__init__.py
collective.bouncing.egg-info/PKG-INFO
collective.bouncing.egg-info/SOURCES.txt
collective.bouncing.egg-info/dependency_links.txt
collective.bouncing.egg-info/entry_points.txt
collective.bouncing.egg-info/namespace_packages.txt
collective.bouncing.egg-info/not-zip-safe
collective.bouncing.egg-info/requires.txt
collective.bouncing.egg-info/top_level.txt
collective/bouncing/README.txt
collective/bouncing/__init__.py
collective/bouncing/api.py
collective/bouncing/channel.py
collective/bouncing/configure.zcml
collective/bouncing/interfaces.py
collective/bouncing/push.py
collective/bouncing/tests.py
collective/bouncing/browser/__init__.py
collective/bouncing/browser/configure.zcml
collective/bouncing/browser/form.pt
collective/bouncing/browser/form.py
collective/bouncing/browser/interfaces.py
collective/bouncing/browser/portlet.pt
collective/bouncing/browser/portlet.py
collective/bouncing/browser/traversal.py
collective/bouncing/locales/collective.bouncing.pot
collective/bouncing/locales/da/LC_MESSAGES/collective.bouncing.po
collective/bouncing/profiles/default/metadata.xml
collective/bouncing/profiles/default/portlets.xml