Metadata-Version: 1.0
Name: collective.bouncing
Version: 0.1.2
Summary: Mailinglist-integration with collective.singing.
Home-page: UNKNOWN
Author: Malthe Borch
Author-email: mborch@gmail.com
License: GPL
Platform: UNKNOWN
Classifier: Framework :: Plone
Classifier: Framework :: Zope2
Classifier: Framework :: Zope3
Classifier: Programming Language :: Python
Classifier: Topic :: Software Development :: Libraries :: Python Modules
